Workbook

Sheet Read Me
B2: Nestly — Unit Economics Model
B3: Jaipur launch · illustrative, built from published market rates — replace every blue cell with Nestly's own numbers
B6: What this is
B7: A costed per-revenue-type model, referenced by docs/MARKET.md §3 and docs/LAUNCH-READINESS-AUDIT.md.
B8: MARKET.md's own figures were market-derived estimates standing in for a model Nestly needs to own — this is that model.
B10: How to use it
B11: 1. Open the 'Assumptions' tab. Every BLUE cell is an input — replace with Nestly's real numbers as they become available.
B12: 2. Open 'Revenue Streams'. Blue cells there are per-stream inputs (price, frequency, CAC). Black cells are formulas — do not overwrite them.
B13: 3. 'Summary' recomputes automatically from the two tabs above — nothing to edit there.
B15: Color key
B16: Blue text = input, edit freely. Black text = formula, do not overwrite. Yellow fill = a figure worth checking first.
B18: Sources for the starting values
... B33: a number from this model, open it once and confirm the Summary tab's figures look sane against the hand-check above.

Sheet Assumptions
B2: Global Assumptions
B3: Edit every BLUE cell. Every Revenue Streams formula reads from here — nothing is hardcoded in a formula.
B5: Assumption | C5: Value | D5: Notes / Source
B6: Platform take rate — consumer jobs | C6: 0.2 | D6: MARKET.md §3: '~20% take' on one-off consumer jobs. Urban Company's Indian consumer take is materially higher; Nestly's stated differentiator is a lower rate — see docs/PRICING.md.
B7: Platform take rate — contract revenue (AMC/B2B/RWA) | C7: 0.35 | D7: Illustrative facility-services-style margin, not a published Nestly rate. Contract revenue is typically higher-margin than spot consumer jobs because utilisation is predictable.
B8: Payment gateway fee | C8: 0.02 | D8: Typical Indian payment-gateway blended fee (Razorpay/PayU card+UPI blend, ~1.8-2.2%). Replace with Nestly's actual negotiated rate.
B9: Support cost per booking | C9: 15 | D9: Placeholder — no real support-cost accounting exists yet (LAUNCH-READINESS-AUDIT.md gap). Replace once support-ticket volume/cost data exists.
B10: Redo / refund provision (% of take) | C10: 0.1 | D10: Placeholder allowance for redo visits and refunds against platform revenue. Replace with actual redo/refund rate once tracked.
B11: Blended CAC — consumer (one-off / repeat) | C11: 450 | D11: MARKET.md §3: 'realistic ₹300-600 acquisition cost'. Midpoint used; edit to your actual blended paid+organic CAC.
B12: Blended CAC — AMC / household plan | C12: 450 | D12: Same acquisition channel as a consumer job (app installs, category browse) — the difference is downstream monetisation, not acquisition cost.
B13: B2B / RWA sales cost per signed contract | C13: 8000 | D13: A field-sales cost (rep time, site visits, proposal), not a marketing CAC — MARKET.md move #1/#2 assumes door-to-door society/site sales, not paid acquisition.
B14: Average customer lifetime (consumer, years) | C14: 2 | D14: For LTV:CAC — edit once real cohort retention data exists. 2 years is a starting assumption, not measured.
B15: Average AMC renewal rate | C15: 0.55 | D15: Industry AMC benchmark context (MARKET.md: 15-25% of AMC revenue lost to missed renewals industry-wide, i.e. ~75-85% naive renewal ceiling); 55% is a conservative planning assumption pending real data.
B16: Average B2B/RWA contract length (years) | C16: 2 | D16: Facility-management contracts commonly renew 1-3 years; edit once Nestly has signed contracts to measure against.

Sheet Revenue Streams
B2: Revenue Streams — Annual Contribution per Acquired Relationship
B3: Blue cells = per-stream inputs. Black cells = formulas reading Assumptions + the blue cells in this sheet.
B5: Revenue Type | C5: Price / Ticket | D5: Visits or Billings / Yr | E5: Annual Booking Value | F5: Take Rate | G5: Gross Platform Revenue | H5: Less: Gateway Fee | I5: Less: Support Cost | J5: Less: Redo/Refund Provision | K5: Contribution Margin | L5: CAC | M5: CAC Payback (x) | N5: Est. Lifetime (yrs) | O5: Lifetime Value (LTV) | P5: LTV : CAC
B6: One-off consumer job | C6: 599 | D6: 1 | E6: =C6*D6 | F6: =Assumptions!$C$6 | G6: =E6*F6 | H6: =E6*Assumptions!$C$8 | I6: =D6*Assumptions!$C$9 | J6: =G6*Assumptions!$C$10 | K6: =G6-H6-I6-J6 | L6: =Assumptions!$C$11 | M6: =IFERROR(K6/L6,0) | N6: =1 | O6: =K6*N6 | P6: =IFERROR(O6/L6,0)
B7: Repeat app customer | C7: 599 | D7: 4 | E7: =C7*D7 | F7: =Assumptions!$C$6 | G7: =E7*F7 | H7: =E7*Assumptions!$C$8 | I7: =D7*Assumptions!$C$9 | J7: =G7*Assumptions!$C$10 | K7: =G7-H7-I7-J7 | L7: =Assumptions!$C$11 | M7: =IFERROR(K7/L7,0) | N7: =Assumptions!$C$14 | O7: =K7*N7 | P7: =IFERROR(O7/L7,0)
B8: AMC contract (annual) | C8: 3499 | D8: 1 | E8: =C8*D8 | F8: =Assumptions!$C$7 | G8: =E8*F8 | H8: =E8*Assumptions!$C$8 | I8: =D8*Assumptions!$C$9 | J8: =G8*Assumptions!$C$10 | K8: =G8-H8-I8-J8 | L8: =Assumptions!$C$12 | M8: =IFERROR(K8/L8,0) | N8: =MIN(10,1/(1-Assumptions!$C$15)) | O8: =K8*N8 | P8: =IFERROR(O8/L8,0)
B9: Household recurring plan (weekly) | C9: 500 | D9: 45 | E9: =C9*D9 | F9: =Assumptions!$C$7 | G9: =E9*F9 | H9: =E9*Assumptions!$C$8 | I9: =D9*Assumptions!$C$9 | J9: =G9*Assumptions!$C$10 | K9: =G9-H9-I9-J9 | L9: =Assumptions!$C$12 | M9: =IFERROR(K9/L9,0) | N9: =Assumptions!$C$14 | O9: =K9*N9 | P9: =IFERROR(O9/L9,0)
B10: B2B site contract (monthly) | C10: 35000 | D10: 12 | E10: =C10*D10 | F10: =Assumptions!$C$7 | G10: =E10*F10 | H10: =E10*Assumptions!$C$8 | I10: =D10*Assumptions!$C$9 | J10: =G10*Assumptions!$C$10 | K10: =G10-H10-I10-J10 | L10: =Assumptions!$C$13 | M10: =IFERROR(K10/L10,0) | N10: =Assumptions!$C$16 | O10: =K10*N10 | P10: =IFERROR(O10/L10,0)
B11: Society / RWA contract (monthly) | C11: 65000 | D11: 12 | E11: =C11*D11 | F11: =Assumptions!$C$7 | G11: =E11*F11 | H11: =E11*Assumptions!$C$8 | I11: =D11*Assumptions!$C$9 | J11: =G11*Assumptions!$C$10 | K11: =G11-H11-I11-J11 | L11: =Assumptions!$C$13 | M11: =IFERROR(K11/L11,0) | N11: =Assumptions!$C$16 | O11: =K11*N11 | P11: =IFERROR(O11/L11,0)
B13: Notes
B14: Gateway fee and redo/refund provision are applied against Annual Booking Value / Gross Platform Revenue respectively — adjust the formulas directly (not just the Assumptions inputs) if Nestly's actual fee basis differs.
B15: 'Household recurring plan' uses 45 visits/yr (not 52) to allow for skipped weeks — a planning assumption, not measured. 'AMC' lifetime is derived from the renewal-rate assumption (1 / (1 - renewal rate), capped at 10 years) rather than a flat input.

Sheet Summary
B2: Summary — Contribution Margin by Revenue Type
B3: Fully computed from Revenue Streams — nothing to edit here.
B5: Revenue Type | C5: Contribution Margin | D5: CAC Payback | E5: LTV : CAC | F5: Verdict
B6: ='Revenue Streams'!B6 | C6: ='Revenue Streams'!K6 | D6: ='Revenue Streams'!M6 | E6: ='Revenue Streams'!P6 | F6: =IF(C6<0,"Loses money",IF(E6>=3,"Strong","Marginal"))
B7: ='Revenue Streams'!B7 | C7: ='Revenue Streams'!K7 | D7: ='Revenue Streams'!M7 | E7: ='Revenue Streams'!P7 | F7: =IF(C7<0,"Loses money",IF(E7>=3,"Strong","Marginal"))
B8: ='Revenue Streams'!B8 | C8: ='Revenue Streams'!K8 | D8: ='Revenue Streams'!M8 | E8: ='Revenue Streams'!P8 | F8: =IF(C8<0,"Loses money",IF(E8>=3,"Strong","Marginal"))
B9: ='Revenue Streams'!B9 | C9: ='Revenue Streams'!K9 | D9: ='Revenue Streams'!M9 | E9: ='Revenue Streams'!P9 | F9: =IF(C9<0,"Loses money",IF(E9>=3,"Strong","Marginal"))
B10: ='Revenue Streams'!B10 | C10: ='Revenue Streams'!K10 | D10: ='Revenue Streams'!M10 | E10: ='Revenue Streams'!P10 | F10: =IF(C10<0,"Loses money",IF(E10>=3,"Strong","Marginal"))
B11: ='Revenue Streams'!B11 | C11: ='Revenue Streams'!K11 | D11: ='Revenue Streams'!M11 | E11: ='Revenue Streams'!P11 | F11: =IF(C11<0,"Loses money",IF(E11>=3,"Strong","Marginal"))
B13: Multiple: top vs. bottom row | C13: =MAX(C6:C11)/C6
B14: Read against MARKET.md §3's illustrative ~2,000x spread between one-off jobs and society contracts — this cell recomputes that ratio from the assumptions above, not the market-derived figure.
